README.md
setup.py
async_pool/__init__.py
async_pool/utils.py
async_pool.egg-info/PKG-INFO
async_pool.egg-info/SOURCES.txt
async_pool.egg-info/dependency_links.txt
async_pool.egg-info/top_level.txt