Metadata-Version: 1.2
Name: async-pool
Version: 0.1.2
Summary: A simple wrapper of library asyncio providing a multiprocessing-library-like coroutine worker pool.
Home-page: https://github.com/gwy15/async_pool
Author: gwy15
Author-email: gwy15thu@gmail.com
License: MIT Licence
Keywords: async,multiprocessing,producer-consumer
Platform: any
Requires-Python: >=3.7
